README.rst
cprofread.py
cprofscan.py
setup.py
pyprofilehelper.egg-info/PKG-INFO
pyprofilehelper.egg-info/SOURCES.txt
pyprofilehelper.egg-info/dependency_links.txt
pyprofilehelper.egg-info/top_level.txt